turkcepython/__init__.py
turkcepyallcommands-1.0.1.dist-info/METADATA
turkcepyallcommands-1.0.1.dist-info/WHEEL
turkcepyallcommands-1.0.1.dist-info/top_level.txt
turkcepyallcommands-1.0.1.dist-info/RECORD
